amazon_lex_bot_test/__init__.py
amazon_lex_bot_test/amazon_lex_bot_test.py
amazon_lex_bot_test/examples/BookTrip_Test.yaml
amazon_lex_bot_test/examples/OrderFlowers_Test.yaml
amazon_lex_bot_test/examples/ScheduleAppointment_Test.yaml
amazon_lex_bot_test-0.1.1.data/scripts/lex-bot-test
amazon_lex_bot_test-0.1.1.dist-info/LICENSE
amazon_lex_bot_test-0.1.1.dist-info/METADATA
amazon_lex_bot_test-0.1.1.dist-info/WHEEL
amazon_lex_bot_test-0.1.1.dist-info/top_level.txt
amazon_lex_bot_test-0.1.1.dist-info/RECORD
