Metadata-Version: 2.1
Name: amazon-lex-bot-test
Version: 0.1.1
Summary: Test Amazon Lex bots easily by defining business requirements through conversations.
Home-page: https://github.com/aws-samples/amazon_lex_bot_test
Author: Martin Schade
Author-email: amazon-lex-bot-test@amazon.com
License: MIT license
Keywords: amazon_lex_bot_test
Platform: UNKNOWN
Classifier: Development Status :: 2 - Pre-Alpha
Classifier: Intended Audience :: Developers
Classifier: License :: OSI Approved :: MIT License
Classifier: Natural Language :: English
Classifier: Programming Language :: Python :: 2
Classifier: Programming Language :: Python :: 2.7
Classifier: Programming Language :: Python :: 3
Classifier: Programming Language :: Python :: 3.4
Classifier: Programming Language :: Python :: 3.5
Classifier: Programming Language :: Python :: 3.6
Classifier: Programming Language :: Python :: 3.7
Requires-Dist: boto3
Requires-Dist: PyYAML
Requires-Dist: botocore
